maurice/__init__.py
maurice/caching.py
maurice/helpers.py
maurice/patchers/__init__.py
maurice/patchers/core.py
maurice/patchers/keras.py
maurice/patchers/pandas.py
maurice/patchers/sklearn.py
maurice/types.py
maurice/utils.py
maurice-0.1.16.dist-info/WHEEL
maurice-0.1.16.dist-info/METADATA
maurice-0.1.16.dist-info/RECORD
