Metadata-Version: 2.1
Name: maurice
Version: 0.1.16
Summary: Ship better machine learning projects, faster!
Home-page: https://github.com/tpvasconcelos/maurice
Author: Tomas Pereira de Vasconcelos
Author-email: tomasvasconcelos1@gmail.com
Requires-Python: >=3.7.1,<4.0.0
Classifier: Programming Language :: Python :: 3
Classifier: Programming Language :: Python :: 3.8
Classifier: Programming Language :: Python :: 3.9
Provides-Extra: all
Provides-Extra: pandas
Provides-Extra: sklearn
Provides-Extra: tensorflow
Requires-Dist: dill (>=0.3.1,<0.4.0)
Requires-Dist: numpy (>=1.19.5,<2.0.0)
Requires-Dist: pandas (>=1.0.0,<2.0.0); extra == "pandas" or extra == "all"
Requires-Dist: scikit-learn; extra == "sklearn" or extra == "all"
Requires-Dist: scipy (>=1.6.0,<2.0.0)
Requires-Dist: tensorflow (>=2.4.0,<3.0.0); extra == "tensorflow" or extra == "all"
Requires-Dist: wrapt (>=1.12.1,<2.0.0)
Project-URL: Repository, https://github.com/tpvasconcelos/maurice
